libssp/__init__.py
libssp/_libssp.cp313-win_amd64.pyd
libssp/libssp.dll
libssp/sspclient.py
libssp-0.1.0.dist-info/licenses/LICENSE
libssp-0.1.0.dist-info/METADATA
libssp-0.1.0.dist-info/WHEEL
libssp-0.1.0.dist-info/top_level.txt
libssp-0.1.0.dist-info/RECORD
