Metadata-Version: 2.4
Name: libssp
Version: 0.1.0
Summary: Python wrapper for libssp
Home-page: https://github.com/Jack-vexel-ws/pylibssp
Author: Jack-vexel
Author-email: jack.vexel@gmail.com
License: MIT
Classifier: Programming Language :: Python :: 3
Classifier: Programming Language :: C++
Classifier: Operating System :: OS Independent
Requires-Python: >=3.7
License-File: LICENSE
Dynamic: license-file
